setup.py
src/django_rax.egg-info/PKG-INFO
src/django_rax.egg-info/SOURCES.txt
src/django_rax.egg-info/dependency_links.txt
src/django_rax.egg-info/not-zip-safe
src/django_rax.egg-info/requires.txt
src/django_rax.egg-info/top_level.txt
src/rax/__init__.py
src/rax/mixin.py
src/rax/storage.py
src/rax/management/__init__.py
src/rax/management/commands/__init__.py
src/rax/management/commands/raxsync.py