Metadata-Version: 1.1
Name: django-rax
Version: 0.4
Summary: PyRax implementation for Django.
Home-page: https://github.com/dustinfarris/django-rax
Author: Dustin Farris
Author-email: dustin@dustinfarris.com
License: BSD
Platform: UNKNOWN
Classifier: Framework :: Django
